tickterial/__init__.py
tickterial/main.py
tickterial/ticker.py
tickterial/tickloader.py
tickterial-1.1.2.dist-info/LICENSE
tickterial-1.1.2.dist-info/METADATA
tickterial-1.1.2.dist-info/WHEEL
tickterial-1.1.2.dist-info/entry_points.txt
tickterial-1.1.2.dist-info/top_level.txt
tickterial-1.1.2.dist-info/RECORD
