Metadata-Version: 2.1
Name: tickterial
Version: 1.1.2
Summary: Download tick data from Dukascopy Bank SA to local cache, and simulate multi-symbol time-ordered price streams to stdout.
Author-email: drui9 <drui9@duck.com>
License: MIT License
Project-URL: Homepage, https://github.com/drui9/tickterial
Keywords: tick-data,forex-data,tick-api,ticks
Classifier: License :: OSI Approved :: MIT License
Classifier: Programming Language :: Python
Classifier: Programming Language :: Python :: 3
Requires-Python: >=3.10
License-File: LICENSE
Requires-Dist: loguru ==0.7.2
Requires-Dist: pytz ==2022.7
Requires-Dist: requests ==2.32.2
Requires-Dist: alive-progress >=3.1.5
Provides-Extra: dev
Requires-Dist: build ; extra == 'dev'
Requires-Dist: twine ; extra == 'dev'
